CHANGES.txt
MANIFEST.in
README.txt
setup.py
js/__init__.py
js.jquery_interdependencies.egg-info/PKG-INFO
js.jquery_interdependencies.egg-info/SOURCES.txt
js.jquery_interdependencies.egg-info/dependency_links.txt
js.jquery_interdependencies.egg-info/entry_points.txt
js.jquery_interdependencies.egg-info/namespace_packages.txt
js.jquery_interdependencies.egg-info/not-zip-safe
js.jquery_interdependencies.egg-info/requires.txt
js.jquery_interdependencies.egg-info/top_level.txt
js/jquery_interdependencies/__init__.py
js/jquery_interdependencies/test_jquery_interdependencies.txt
js/jquery_interdependencies/resources/jquery.interdependencies.js