Metadata-Version: 1.1
Name: js.jquery-interdependencies
Version: 0.1
Summary: Fanstatic packaging of jQuery Interdependencies.
Home-page: https://bitbucket.org/it_spirit/js.jquery_interdependencies
Author: Thomas Massmann
Author-email: thomas.massmann@it-spir.it
License: BSD
Download-URL: http://pypi.python.org/pypi/js.jquery_interdependencies
Platform: UNKNOWN
